picklellc/__init__.py
picklellc/picklellc.py
pickellc-0.2.0.dist-info/METADATA
pickellc-0.2.0.dist-info/WHEEL
pickellc-0.2.0.dist-info/top_level.txt
pickellc-0.2.0.dist-info/RECORD
