Metadata-Version: 2.1
Name: pickellc
Version: 0.2.0
Summary: Python client for Pickle LLC API
Author: Pickle LLC
Author-email: peterfarag12@gmail.com
Classifier: Programming Language :: Python :: 3
Classifier: License :: OSI Approved :: MIT License
Classifier: Operating System :: OS Independent
Requires-Python: >=3.6
Requires-Dist: requests
Requires-Dist: numpy
